pyorc/__init__.py
pyorc/const.py
pyorc/cv.py
pyorc/helpers.py
pyorc/plot_helpers.py
pyorc/project.py
pyorc/pyorc.sh
pyorc/sample_data.py
pyorc/api/__init__.py
pyorc/api/cameraconfig.py
pyorc/api/cross_section.py
pyorc/api/frames.py
pyorc/api/mask.py
pyorc/api/orcbase.py
pyorc/api/plot.py
pyorc/api/transect.py
pyorc/api/velocimetry.py
pyorc/api/video.py
pyorc/cli/__init__.py
pyorc/cli/cli_elements.py
pyorc/cli/cli_utils.py
pyorc/cli/log.py
pyorc/cli/main.py
pyorc/service/__init__.py
pyorc/service/camera_config.py
pyorc/service/velocimetry.py
pyorc/velocimetry/__init__.py
pyorc/velocimetry/ffpiv.py
pyopenrivercam-0.9.2.dist-info/entry_points.txt
pyopenrivercam-0.9.2.dist-info/licenses/LICENSE
pyopenrivercam-0.9.2.dist-info/WHEEL
pyopenrivercam-0.9.2.dist-info/METADATA
pyopenrivercam-0.9.2.dist-info/RECORD
