Metadata-Version: 2.4
Name: pyopenrivercam
Version: 0.9.2
Summary: pyorc: free and open-source image-based surface velocity and discharge.
Author-email: Hessel Winsemius <winsemius@rainbowsensing.com>
Requires-Python: >=3.9
Classifier: Development Status :: 5 - Production/Stable
Classifier: Intended Audience :: Developers
Classifier: Intended Audience :: Science/Research
Classifier: Topic :: Scientific/Engineering :: Hydrology
Classifier: Topic :: Scientific/Engineering :: Image Processing
Classifier: License :: OSI Approved :: GNU Affero General Public License v3
Classifier: Programming Language :: Python :: 3
Classifier: Programming Language :: Python :: 3.9
Classifier: Programming Language :: Python :: 3.10
Classifier: Programming Language :: Python :: 3.11
Classifier: Programming Language :: Python :: 3.12
License-File: LICENSE
Requires-Dist: click
Requires-Dist: cython; platform_machine == 'armv7l'
Requires-Dist: dask
Requires-Dist: descartes
Requires-Dist: ffpiv>=0.2.0
Requires-Dist: flox
Requires-Dist: geojson
Requires-Dist: geopandas
Requires-Dist: matplotlib
Requires-Dist: netCDF4
Requires-Dist: numba>0.56
Requires-Dist: numpy==1.26.4; python_version == '3.9'
Requires-Dist: numpy>=2; python_version >= '3.10'
Requires-Dist: opencv-python
Requires-Dist: packaging; platform_machine == 'armv7l'
Requires-Dist: pillow==9.5.0; python_version == '3.9'
Requires-Dist: pillow; python_version >= '3.10'
Requires-Dist: pip
Requires-Dist: pyproj
Requires-Dist: pythran; platform_machine == 'armv7l'
Requires-Dist: pyyaml
Requires-Dist: rasterio<1.4.0; python_version <= '3.12'
Requires-Dist: rasterio; python_version > '3.12'
Requires-Dist: scipy
Requires-Dist: shapely
Requires-Dist: tqdm
Requires-Dist: typeguard
Requires-Dist: xarray
Requires-Dist: sphinx==5.3 ; extra == "docs"
Requires-Dist: sphinx_autosummary_accessors ; extra == "docs"
Requires-Dist: sphinxcontrib-programoutput ; extra == "docs"
Requires-Dist: sphinx_rtd_theme ; extra == "docs"
Requires-Dist: sphinx-design ; extra == "docs"
Requires-Dist: pydata_sphinx_theme ; extra == "docs"
Requires-Dist: ipykernel ; extra == "docs"
Requires-Dist: nbsphinx ; extra == "docs"
Requires-Dist: sphinx-gallery ; extra == "docs"
Requires-Dist: pandoc ; extra == "docs"
Requires-Dist: pooch ; extra == "docs"
Requires-Dist: matplotlib ; extra == "docs"
Requires-Dist: notebook ; extra == "extra"
Requires-Dist: cartopy ; extra == "extra"
Requires-Dist: pooch ; extra == "extra"
Requires-Dist: pyopenrivercam[extra, test, docs] ; extra == "full"
Requires-Dist: pytest ; extra == "test"
Requires-Dist: pytest-cov ; extra == "test"
Requires-Dist: pooch ; extra == "test"
Project-URL: Source, https://github.com/localdevices/pyorc
Provides-Extra: docs
Provides-Extra: extra
Provides-Extra: full
Provides-Extra: test
